<?xml version="1.0" encoding="utf-8" ?>
<dwsync>
<file name="control.js" server="116.52.157.138" local="129635074503274491" remote="129651240000000000" />
<file name="dialog.js" server="116.52.157.138" local="129152760560000000" remote="129651240000000000" />
<file name="HiberarchyRender.js" server="116.52.157.138" local="129152760560000000" remote="129651240000000000" />
<file name="html_editor.js" server="116.52.157.138" local="129650086547849307" remote="129651240000000000" />
<file name="html_editor.old.js" server="116.52.157.138" local="129621133350170494" remote="129651240000000000" />
<file name="html_page.js" server="116.52.157.138" local="129152760580000000" remote="129651240000000000" />
<file name="index.html" server="116.52.157.138" local="129152776740000000" remote="129651240000000000" />
<file name="listview.js" server="116.52.157.138" local="129189792740000000" remote="129651240000000000" />
<file name="listview_old.js" server="116.52.157.138" local="129173293940000000" remote="129651240000000000" />
<file name="pic_marquee.js" server="116.52.157.138" local="129648137773575936" remote="129651366000000000" />
<file name="property_list.js" server="116.52.157.138" local="129157302580000000" remote="129651240000000000" />
<file name="shape.js" server="116.52.157.138" local="129636148028269019" remote="129651240000000000" />
<file name="tablelist.js" server="116.52.157.138" local="129152820320000000" remote="129651240000000000" />
<file name="tab_control.js" server="116.52.157.138" local="129652654521909136" remote="129652655400000000" />
<file name="tab_page.js" server="116.52.157.138" local="129152760580000000" remote="129651240000000000" />
<file name="wbdl_editor.js" server="116.52.157.138" local="129627727983370475" remote="129651240600000000" />
<file name="xlistview.js" server="116.52.157.138" local="129629620449014764" remote="129651240600000000" />
<file name="chine_date.js" server="116.52.157.138" local="129652627841553107" remote="129652633200000000" />
</dwsync>