<?xml version="1.0" encoding="utf-8"?><WboSchema xmlns:xsi="http://www.w3.org/2001/XMLSchema-instance" xmlns:xsd="http://www.w3.org/2001/XMLSchema"><Id>WxJsCfg</Id><Title>WxJsCfg</Title><Methods><WboMethodSchema><Id>ToString</Id><Title>ToString</Title><PermissionTypes>Read</PermissionTypes><ExecuteType>none</ExecuteType><Params /><ReturnType>System.String</ReturnType></WboMethodSchema><WboMethodSchema><Id>Equals</Id><Title>Equals</Title><PermissionTypes>Read</PermissionTypes><ExecuteType>none</ExecuteType><Params><WboMethodParamSchema><Id>obj</Id><Title>obj</Title><DefaultValue /><DataType>System.Object, mscorlib, Version=4.0.0.0, Culture=neutral, PublicKeyToken=b77a5c561934e089</DataType></WboMethodParamSchema></Params><ReturnType>System.Boolean</ReturnType></WboMethodSchema><WboMethodSchema><Id>GetHashCode</Id><Title>GetHashCode</Title><PermissionTypes>Read</PermissionTypes><ExecuteType>none</ExecuteType><Params /><ReturnType>System.Int32</ReturnType></WboMethodSchema><WboMethodSchema><Id>GetType</Id><Title>GetType</Title><PermissionTypes>Read</PermissionTypes><ExecuteType>none</ExecuteType><Params /><ReturnType>System.Type</ReturnType></WboMethodSchema></Methods><PermissionTypes>Read</PermissionTypes><Namespace>xbase.weixin.jssdk</Namespace><AssemblyCategory>DotNet</AssemblyCategory><Src>C:\Users\lov\AppData\Local\Temp\Temporary ASP.NET Files\vs\edc108a6\bea8ec4d\assembly\dl3\fda76c19\c4d6db27_ab4cd201\xbase.weixin.dll</Src><IsVisual>false</IsVisual><IsPublish>false</IsPublish><Properties><Schema><Id>appId</Id></Schema><Schema><Id>timestamp</Id></Schema><Schema><Id>nonceStr</Id></Schema><Schema><Id>signature</Id></Schema></Properties><LifeCycle>Request</LifeCycle><AssemblyName>xbase.weixin, Version=1.0.0.0, Culture=neutral, PublicKeyToken=null</AssemblyName><ClassName>xbase.weixin.jssdk.WxJsApiConfig</ClassName></WboSchema>